model_constructor/__init__.py
model_constructor/activations.py
model_constructor/base_constructor.py
model_constructor/blocks.py
model_constructor/convmixer.py
model_constructor/helpers.py
model_constructor/layers.py
model_constructor/model_constructor.py
model_constructor/mxresnet.py
model_constructor/net.py
model_constructor/twist.py
model_constructor/universal_blocks.py
model_constructor/version.py
model_constructor/xresnet.py
model_constructor/yaresnet.py
model_constructor-0.4.1.dist-info/LICENSE
model_constructor-0.4.1.dist-info/METADATA
model_constructor-0.4.1.dist-info/WHEEL
model_constructor-0.4.1.dist-info/top_level.txt
model_constructor-0.4.1.dist-info/RECORD
