Metadata-Version: 2.1
Name: model-constructor
Version: 0.4.1
Summary: Pytorch models constructor.
Home-page: https://github.com/ayasyrev/model_constructor
Author: Yasyrev Andrei
Author-email: a.yasyrev@gmail.com
License: apache2
Keywords: pytorch models
Classifier: Programming Language :: Python :: 3
Classifier: License :: OSI Approved :: Apache Software License
Classifier: Operating System :: OS Independent
Requires-Python: >=3.7
License-File: LICENSE
Provides-Extra: test
